reobject/__init__.py
reobject/transaction.py
reobject/types.py
reobject/utils.py
reobject/exceptions/__init__.py
reobject/models/__init__.py
reobject/models/fields.py
reobject/models/manager.py
reobject/models/model.py
reobject/models/store.py
reobject/query/__init__.py
reobject/query/parser.py
reobject/query/queryset.py
reobject-0.9a7.dist-info/LICENSE
reobject-0.9a7.dist-info/METADATA
reobject-0.9a7.dist-info/WHEEL
reobject-0.9a7.dist-info/top_level.txt
reobject-0.9a7.dist-info/RECORD
