Metadata-Version: 2.1
Name: reobject
Version: 0.9a7
Summary: Python without ifs and buts
Home-page: https://github.com/onyb/reobject
Author: Anirudha Bose
Author-email: ani07nov@gmail.com
License: Apache-2.0
Keywords: orm,python,object-oriented-programming,django
Platform: UNKNOWN
Classifier: Development Status :: 3 - Alpha
Classifier: Intended Audience :: Developers
Classifier: Topic :: Software Development :: Libraries
Classifier: License :: OSI Approved :: Apache Software License
Classifier: Programming Language :: Python :: 3
Classifier: Programming Language :: Python :: 3.3
Classifier: Programming Language :: Python :: 3.4
Classifier: Programming Language :: Python :: 3.5
Classifier: Programming Language :: Python :: 3.6
Requires-Dist: attrs (>=17.2.0)
